[
    {
        "var_rgp":"BAC",
        "var_sise":"acabac",
        "n_data":"N_ACADEMIE_ET_ASSIMILE",
        "format":"str",
        "missing_value":"-1",
        "empty":""
    },
    {
        "var_rgp":"BAC",
        "var_sise":"anbac",
        "n_data":"",
        "format":"int",
        "missing_value":-1,
        "empty":""
    },
    {
        "var_rgp":"BAC",
        "var_sise":"bac",
        "n_data":"N_BAC",
        "format":"str",
        "missing_value":"-1",
        "empty":""
    },
    {
        "var_rgp":"BAC",
        "var_sise":"bac_rgrp",
        "n_data":"N_BAC_REGROUPE_2",
        "format":"str",
        "missing_value":"-1",
        "empty":""
    },
    {
        "var_rgp":"BAC",
        "var_sise":"bac_spe1",
        "n_data":"N_SPECIALITE_BAC_2021_SISE",
        "format":"str",
        "missing_value":"-1",
        "empty":""
    },
    {
        "var_rgp":"BAC",
        "var_sise":"bac_spe2",
        "n_data":"N_SPECIALITE_BAC_2021_SISE",
        "format":"str",
        "missing_value":"-1",
        "empty":""
    },
    {
        "var_rgp":"BAC",
        "var_sise":"depbac",
        "n_data":"N_DEPARTEMENT",
        "format":"str",
        "missing_value":"-1",
        "empty":""
    },
    {
        "var_rgp":"COMPTE",
        "var_sise":"effectif",
        "n_data":"",
        "format":"int",
        "missing_value":-1,
        "empty":"NO"
    },
    {
        "var_rgp":"COMPTE",
        "var_sise":"inspr",
        "n_data":"N_INSCRIPTION_PRINCIPALE",
        "format":"str",
        "missing_value":"",
        "empty":"NO"
    },
    {
        "var_rgp":"COMPTE",
        "var_sise":"nbach",
        "n_data":"",
        "format":-1,
        "missing_value":"",
        "empty":""
    },
    {
        "var_rgp":"COMPTE",
        "var_sise":"net",
        "n_data":"",
        "format":"int",
        "missing_value":-1,
        "empty":""
    },
    {
        "var_rgp":"ETABLISSEMENT",
        "var_sise":"cometa",
        "n_data":"LES_COMMUNES",
        "format":"str",
        "missing_value":"",
        "empty":"NO"
    },
    {
        "var_rgp":"ETABLISSEMENT",
        "var_sise":"comins",
        "n_data":"LES_COMMUNES",
        "format":"str",
        "missing_value":"",
        "empty":"NO"
    },
    {
        "var_rgp":"ETABLISSEMENT",
        "var_sise":"compos",
        "n_data":"N_BCE_SISE_N",
        "format":"str",
        "missing_value":"",
        "empty":"NO"
    },
    {
        "var_rgp":"ETABLISSEMENT",
        "var_sise":"etabli",
        "n_data":"PAYSAGE_id",
        "format":"str",
        "missing_value":"",
        "empty":""
    },
    {
        "var_rgp":"ETABLISSEMENT",
        "var_sise":"etabli_diffusion",
        "n_data":"",
        "format":"str",
        "missing_value":"",
        "empty":""
    },
    {
        "var_rgp":"ETABLISSEMENT",
        "var_sise":"numed",
        "n_data":"",
        "format":"str",
        "missing_value":"",
        "empty":""
    },
    {
        "var_rgp":"ETABLISSEMENT",
        "var_sise":"oppos",
        "n_data":"N_OPPOSITION",
        "format":"str",
        "missing_value":"-1",
        "empty":""
    },
    {
        "var_rgp":"ETUDIANT",
        "var_sise":"age",
        "n_data":"",
        "format":"int",
        "missing_value":-1,
        "empty":"NO"
    },
    {
        "var_rgp":"ETUDIANT",
        "var_sise":"annais",
        "n_data":"",
        "format":"int",
        "missing_value":-1,
        "empty":"NO"
    },
    {
        "var_rgp":"ETUDIANT",
        "var_sise":"deprespa",
        "n_data":"N_DEPARTEMENT",
        "format":"str",
        "missing_value":"0",
        "empty":""
    },
    {
        "var_rgp":"ETUDIANT",
        "var_sise":"dipder",
        "n_data":"N_DERNIER_DIPLOME_OBTENU",
        "format":"str",
        "missing_value":"-1",
        "empty":""
    },
    {
        "var_rgp":"ETUDIANT",
        "var_sise":"nation",
        "n_data":"G_PAYS",
        "format":"str",
        "missing_value":"-1",
        "empty":""
    },
    {
        "var_rgp":"ETUDIANT",
        "var_sise":"paripa",
        "n_data":"G_PAYS",
        "format":"str",
        "missing_value":"-1",
        "empty":""
    },
    {
        "var_rgp":"ETUDIANT",
        "var_sise":"pcspar",
        "n_data":"N_PCS",
        "format":"str",
        "missing_value":"99",
        "empty":""
    },
    {
        "var_rgp":"ETUDIANT",
        "var_sise":"pcspar2",
        "n_data":"N_PCS",
        "format":"str",
        "missing_value":"99",
        "empty":""
    },
    {
        "var_rgp":"ETUDIANT",
        "var_sise":"sexe",
        "n_data":"N_SEXE",
        "format":"str",
        "missing_value":"-1",
        "empty":"NO"
    },
    {
        "var_rgp":"ETUDIANT_FORMATION_ANTERIEURE",
        "var_sise":"situpre",
        "n_data":"N_SITUATION_ANNEE_PRECEDENTE",
        "format":"str",
        "missing_value":"9",
        "empty":""
    },
    {
        "var_rgp":"ETUDIANT_FORMATION_ANTERIEURE",
        "var_sise":"typrepa",
        "n_data":"N_TYPE_CLASSE_PREPA_SISE",
        "format":"str",
        "missing_value":"-1",
        "empty":""
    },
    {
        "var_rgp":"FLAG",
        "var_sise":"flag_meef",
        "n_data":"N_MEEF",
        "format":"str",
        "missing_value":"0",
        "empty":""
    },
    {
        "var_rgp":"FLAG",
        "var_sise":"flag_sup",
        "n_data":"N_SUP",
        "format":"str",
        "missing_value":"-1",
        "empty":"NO"
    },
    {
        "var_rgp":"FORMATION",
        "var_sise":"amena",
        "n_data":"N_AMENA",
        "format":"str",
        "missing_value":"-1",
        "empty":""
    },
    {
        "var_rgp":"FORMATION",
        "var_sise":"cursus_lmd",
        "n_data":"N_CURSUS",
        "format":"str",
        "missing_value":"-1",
        "empty":""
    },
    {
        "var_rgp":"FORMATION",
        "var_sise":"cycle",
        "n_data":"N_CYCLE_SISE",
        "format":"str",
        "missing_value":"-1",
        "empty":""
    },
    {
        "var_rgp":"FORMATION",
        "var_sise":"groupe",
        "n_data":"N_GROUPE_DISCIPLINE_SISE",
        "format":"str",
        "missing_value":"",
        "empty":"NO"
    },
    {
        "var_rgp":"FORMATION",
        "var_sise":"nature",
        "n_data":"N_NATURE_DIPLOME_SISE",
        "format":"str",
        "missing_value":"-1",
        "empty":""
    },
    {
        "var_rgp":"FORMATION",
        "var_sise":"niveau_d",
        "n_data":"N_NIVEAU_FORMATION",
        "format":"str",
        "missing_value":"",
        "empty":"NO"
    },
    {
        "var_rgp":"FORMATION",
        "var_sise":"niveau_f",
        "n_data":"N_NIVEAU_FORMATION",
        "format":"str",
        "missing_value":"",
        "empty":"NO"
    },
    {
        "var_rgp":"FORMATION",
        "var_sise":"sectdis",
        "n_data":"DISCIPLINES_SISE",
        "format":"str",
        "missing_value":"",
        "empty":"NO"
    },
    {
        "var_rgp":"FORMATION",
        "var_sise":"typ_dipl",
        "n_data":"N_TYPE_DIPLOME_SISE",
        "format":"str",
        "missing_value":"",
        "empty":"NO"
    },
    {
        "var_rgp":"FORMATION_ETUDIANT",
        "var_sise":"conv",
        "n_data":"N_CONVENTION",
        "format":"str",
        "missing_value":"-1",
        "empty":""
    },
    {
        "var_rgp":"FORMATION_ETUDIANT",
        "var_sise":"curpar",
        "n_data":"N_AUTRE_CURSUS_SISE",
        "format":"str",
        "missing_value":"-1",
        "empty":""
    },
    {
        "var_rgp":"FORMATION_ETUDIANT",
        "var_sise":"degetu",
        "n_data":"N_NIVEAU_FORMATION",
        "format":"str",
        "missing_value":"-1",
        "empty":""
    },
    {
        "var_rgp":"FORMATION_ETUDIANT",
        "var_sise":"echang",
        "n_data":"N_PROGRAMME_ECHANGE_INTERNATIO",
        "format":"str",
        "missing_value":"0",
        "empty":""
    },
    {
        "var_rgp":"FORMATION_ETUDIANT",
        "var_sise":"exoins",
        "n_data":"N_EXONERATIONS",
        "format":"str",
        "missing_value":"-1",
        "empty":""
    },
    {
        "var_rgp":"FORMATION_ETUDIANT",
        "var_sise":"niveau",
        "n_data":"N_ANNEE_DANS_FORMATION_SISE",
        "format":"str",
        "missing_value":"0",
        "empty":""
    },
    {
        "var_rgp":"FORMATION_ETUDIANT",
        "var_sise":"par_type",
        "n_data":"N_PARCOURS_TYPE_SISE",
        "format":"str",
        "missing_value":"-1",
        "empty":""
    },
    {
        "var_rgp":"FORMATION_ETUDIANT",
        "var_sise":"regime",
        "n_data":"N_REGIME_INSCRIPTION",
        "format":"str",
        "missing_value":"-1",
        "empty":""
    },
    {
        "var_rgp":"FORMATION_ETUDIANT",
        "var_sise":"specia",
        "n_data":"N_SPECIALISATION",
        "format":"str",
        "missing_value":"-1",
        "empty":""
    },
    {
        "var_rgp":"FORMATION_ETUDIANT",
        "var_sise":"specib",
        "n_data":"N_SPECIALISATION",
        "format":"str",
        "missing_value":"-1",
        "empty":""
    },
    {
        "var_rgp":"FORMATION_ETUDIANT",
        "var_sise":"specic",
        "n_data":"N_SPECIALISATION",
        "format":"str",
        "missing_value":"-1",
        "empty":""
    },
    {
        "var_rgp":"FORMATION_ETUDIANT",
        "var_sise":"voie",
        "n_data":"N_VOIE_LMD",
        "format":"str",
        "missing_value":"-1",
        "empty":""
    },
    {
        "var_rgp":"FORMATION",
        "var_sise":"diplom",
        "n_data":"N_DIPLOME_SISE",
        "format":"str",
        "missing_value":"-1",
        "empty":""
    }
]